[
  {
    "full_name": "rsocket/rsocket-java",
    "stargazers_count": 2382,
    "open_issues_count": 56,
    "forks_count": 356
  },
  {
    "full_name": "graphql-java/graphql-java",
    "stargazers_count": 6188,
    "open_issues_count": 37,
    "forks_count": 1144
  },
  {
    "full_name": "quarkusio/quarkus",
    "stargazers_count": 14835,
    "open_issues_count": 2630,
    "forks_count": 2926
  },
  {
    "full_name": "apache/camel",
    "stargazers_count": 5924,
    "open_issues_count": 4,
    "forks_count": 5058
  },
  {
    "full_name": "apache/camel-examples",
    "stargazers_count": 451,
    "open_issues_count": 0,
    "forks_count": 380
  }
]