[
  {
    "full_name": "rsocket/rsocket-java",
    "stargazers_count": 2394,
    "open_issues_count": 61,
    "forks_count": 355
  },
  {
    "full_name": "graphql-java/graphql-java",
    "stargazers_count": 6231,
    "open_issues_count": 54,
    "forks_count": 1149
  },
  {
    "full_name": "quarkusio/quarkus",
    "stargazers_count": 15569,
    "open_issues_count": 2679,
    "forks_count": 3116
  },
  {
    "full_name": "apache/camel",
    "stargazers_count": 6158,
    "open_issues_count": 50,
    "forks_count": 5096
  },
  {
    "full_name": "apache/camel-examples",
    "stargazers_count": 472,
    "open_issues_count": 0,
    "forks_count": 378
  }
]