[
  {
    "full_name": "rsocket/rsocket-java",
    "stargazers_count": 2233,
    "open_issues_count": 40,
    "forks_count": 340
  },
  {
    "full_name": "graphql-java/graphql-java",
    "stargazers_count": 5710,
    "open_issues_count": 74,
    "forks_count": 1038
  },
  {
    "full_name": "quarkusio/quarkus",
    "stargazers_count": 11158,
    "open_issues_count": 2115,
    "forks_count": 2077
  },
  {
    "full_name": "apache/camel",
    "stargazers_count": 4654,
    "open_issues_count": 9,
    "forks_count": 4648
  },
  {
    "full_name": "apache/camel-examples",
    "stargazers_count": 293,
    "open_issues_count": 0,
    "forks_count": 308
  }
]