[
  {
    "full_name": "rsocket/rsocket-java",
    "stargazers_count": 2140,
    "open_issues_count": 31,
    "forks_count": 321
  },
  {
    "full_name": "graphql-java/graphql-java",
    "stargazers_count": 5446,
    "open_issues_count": 93,
    "forks_count": 995
  },
  {
    "full_name": "quarkusio/quarkus",
    "stargazers_count": 9616,
    "open_issues_count": 1865,
    "forks_count": 1735
  },
  {
    "full_name": "apache/camel",
    "stargazers_count": 4198,
    "open_issues_count": 7,
    "forks_count": 4490
  },
  {
    "full_name": "apache/camel-examples",
    "stargazers_count": 238,
    "open_issues_count": 0,
    "forks_count": 248
  }
]