[
  {
    "full_name": "cartesi/machine-emulator",
    "stargazers_count": 50,
    "open_issues_count": 39,
    "forks_count": 26
  },
  {
    "full_name": "actions/setup-go",
    "stargazers_count": 1274,
    "open_issues_count": 34,
    "forks_count": 479
  },
  {
    "full_name": "etherparty/explorer",
    "stargazers_count": 623,
    "open_issues_count": 32,
    "forks_count": 401
  },
  {
    "full_name": "blockscout/blockscout",
    "stargazers_count": 3062,
    "open_issues_count": 434,
    "forks_count": 2017
  },
  {
    "full_name": "pascaldekloe/etherstream",
    "stargazers_count": 3,
    "open_issues_count": 1,
    "forks_count": 0
  },
  {
    "full_name": "cosmtrek/air",
    "stargazers_count": 14372,
    "open_issues_count": 136,
    "forks_count": 715
  },
  {
    "full_name": "eko/monday",
    "stargazers_count": 1333,
    "open_issues_count": 2,
    "forks_count": 45
  },
  {
    "full_name": "ethereum/go-ethereum",
    "stargazers_count": 45188,
    "open_issues_count": 362,
    "forks_count": 18716
  },
  {
    "full_name": "prysmaticlabs/prysm",
    "stargazers_count": 3308,
    "open_issues_count": 260,
    "forks_count": 869
  },
  {
    "full_name": "FuelLabs/fuel-core",
    "stargazers_count": 47320,
    "open_issues_count": 160,
    "forks_count": 2093
  },
  {
    "full_name": "foundry-rs/foundry",
    "stargazers_count": 7319,
    "open_issues_count": 937,
    "forks_count": 1392
  },
  {
    "full_name": "ethereum-lists/chains",
    "stargazers_count": 7817,
    "open_issues_count": 81,
    "forks_count": 5328
  },
  {
    "full_name": "charmbracelet/bubbletea",
    "stargazers_count": 22912,
    "open_issues_count": 83,
    "forks_count": 673
  },
  {
    "full_name": "kelseyhightower/envconfig",
    "stargazers_count": 4844,
    "open_issues_count": 52,
    "forks_count": 373
  },
  {
    "full_name": "traefik/traefik",
    "stargazers_count": 47049,
    "open_issues_count": 673,
    "forks_count": 4799
  },
  {
    "full_name": "caddyserver/caddy",
    "stargazers_count": 52644,
    "open_issues_count": 156,
    "forks_count": 3821
  },
  {
    "full_name": "micro/micro",
    "stargazers_count": 11970,
    "open_issues_count": 40,
    "forks_count": 1038
  },
  {
    "full_name": "spf13/spf13-vim",
    "stargazers_count": 15540,
    "open_issues_count": 353,
    "forks_count": 3660
  },
  {
    "full_name": "gofiber/recipes",
    "stargazers_count": 2776,
    "open_issues_count": 15,
    "forks_count": 432
  },
  {
    "full_name": "open-telemetry/semantic-conventions",
    "stargazers_count": 159,
    "open_issues_count": 237,
    "forks_count": 112
  },
  {
    "full_name": "open-telemetry/opentelemetry-go",
    "stargazers_count": 4642,
    "open_issues_count": 155,
    "forks_count": 951
  },
  {
    "full_name": "dapr/docs",
    "stargazers_count": 985,
    "open_issues_count": 105,
    "forks_count": 690
  },
  {
    "full_name": "mathaou/termdbms",
    "stargazers_count": 1620,
    "open_issues_count": 4,
    "forks_count": 36
  },
  {
    "full_name": "vjega/tui-sql-browser",
    "stargazers_count": 7,
    "open_issues_count": 0,
    "forks_count": 1
  },
  {
    "full_name": "fullstorydev/grpcurl",
    "stargazers_count": 9853,
    "open_issues_count": 89,
    "forks_count": 474
  },
  {
    "full_name": "Envoy-VC/blockend-developer-roadmap",
    "stargazers_count": 354,
    "open_issues_count": 0,
    "forks_count": 70
  },
  {
    "full_name": "golang-standards/project-layout",
    "stargazers_count": 44955,
    "open_issues_count": 87,
    "forks_count": 4802
  },
  {
    "full_name": "devnw/gvm",
    "stargazers_count": 56,
    "open_issues_count": 20,
    "forks_count": 4
  },
  {
    "full_name": "golang/mock",
    "stargazers_count": 9197,
    "open_issues_count": 81,
    "forks_count": 609
  },
  {
    "full_name": "cube-js/cube",
    "stargazers_count": 16943,
    "open_issues_count": 849,
    "forks_count": 1671
  }
]