[
  {
    "full_name": "pascaldekloe/etherstream",
    "stargazers_count": 3,
    "open_issues_count": 1,
    "forks_count": 0
  },
  {
    "full_name": "cosmtrek/air",
    "stargazers_count": 13494,
    "open_issues_count": 115,
    "forks_count": 752
  },
  {
    "full_name": "eko/monday",
    "stargazers_count": 1331,
    "open_issues_count": 1,
    "forks_count": 44
  },
  {
    "full_name": "ethereum/go-ethereum",
    "stargazers_count": 44483,
    "open_issues_count": 338,
    "forks_count": 19674
  },
  {
    "full_name": "prysmaticlabs/prysm",
    "stargazers_count": 3281,
    "open_issues_count": 247,
    "forks_count": 951
  },
  {
    "full_name": "FuelLabs/fuel-core",
    "stargazers_count": 30204,
    "open_issues_count": 159,
    "forks_count": 1245
  },
  {
    "full_name": "foundry-rs/foundry",
    "stargazers_count": 7061,
    "open_issues_count": 896,
    "forks_count": 1310
  },
  {
    "full_name": "ethereum-lists/chains",
    "stargazers_count": 7278,
    "open_issues_count": 86,
    "forks_count": 5742
  },
  {
    "full_name": "charmbracelet/bubbletea",
    "stargazers_count": 21869,
    "open_issues_count": 94,
    "forks_count": 660
  },
  {
    "full_name": "kelseyhightower/envconfig",
    "stargazers_count": 4779,
    "open_issues_count": 52,
    "forks_count": 375
  },
  {
    "full_name": "traefik/traefik",
    "stargazers_count": 46168,
    "open_issues_count": 695,
    "forks_count": 4822
  },
  {
    "full_name": "caddyserver/caddy",
    "stargazers_count": 51569,
    "open_issues_count": 143,
    "forks_count": 3929
  },
  {
    "full_name": "micro/micro",
    "stargazers_count": 11944,
    "open_issues_count": 46,
    "forks_count": 1101
  },
  {
    "full_name": "spf13/spf13-vim",
    "stargazers_count": 15531,
    "open_issues_count": 352,
    "forks_count": 3691
  },
  {
    "full_name": "gofiber/recipes",
    "stargazers_count": 2684,
    "open_issues_count": 15,
    "forks_count": 427
  },
  {
    "full_name": "open-telemetry/semantic-conventions",
    "stargazers_count": 142,
    "open_issues_count": 190,
    "forks_count": 99
  },
  {
    "full_name": "open-telemetry/opentelemetry-go",
    "stargazers_count": 4485,
    "open_issues_count": 164,
    "forks_count": 984
  },
  {
    "full_name": "dapr/docs",
    "stargazers_count": 984,
    "open_issues_count": 118,
    "forks_count": 685
  },
  {
    "full_name": "mathaou/termdbms",
    "stargazers_count": 1586,
    "open_issues_count": 4,
    "forks_count": 35
  },
  {
    "full_name": "vjega/tui-sql-browser",
    "stargazers_count": 7,
    "open_issues_count": 0,
    "forks_count": 1
  },
  {
    "full_name": "fullstorydev/grpcurl",
    "stargazers_count": 9593,
    "open_issues_count": 91,
    "forks_count": 463
  },
  {
    "full_name": "Envoy-VC/blockend-developer-roadmap",
    "stargazers_count": 349,
    "open_issues_count": 0,
    "forks_count": 71
  },
  {
    "full_name": "golang-standards/project-layout",
    "stargazers_count": 43848,
    "open_issues_count": 97,
    "forks_count": 4823
  },
  {
    "full_name": "devnw/gvm",
    "stargazers_count": 56,
    "open_issues_count": 20,
    "forks_count": 4
  },
  {
    "full_name": "golang/mock",
    "stargazers_count": 9164,
    "open_issues_count": 81,
    "forks_count": 660
  },
  {
    "full_name": "cube-js/cube",
    "stargazers_count": 16698,
    "open_issues_count": 821,
    "forks_count": 1663
  },
  {
    "full_name": "grafana/tempo",
    "stargazers_count": 3438,
    "open_issues_count": 167,
    "forks_count": 451
  },
  {
    "full_name": "grafana/loki",
    "stargazers_count": 21005,
    "open_issues_count": 1342,
    "forks_count": 3097
  },
  {
    "full_name": "keichi/binary-parser",
    "stargazers_count": 830,
    "open_issues_count": 49,
    "forks_count": 129
  },
  {
    "full_name": "markotom/restify-url-semver",
    "stargazers_count": 20,
    "open_issues_count": 3,
    "forks_count": 14
  }
]