[
  {
    "full_name": "Envoy-VC/blockend-developer-roadmap",
    "stargazers_count": 332,
    "open_issues_count": 0,
    "forks_count": 70
  },
  {
    "full_name": "golang-standards/project-layout",
    "stargazers_count": 39901,
    "open_issues_count": 109,
    "forks_count": 4460
  },
  {
    "full_name": "devnw/gvm",
    "stargazers_count": 53,
    "open_issues_count": 19,
    "forks_count": 4
  },
  {
    "full_name": "golang/mock",
    "stargazers_count": 8942,
    "open_issues_count": 87,
    "forks_count": 616
  },
  {
    "full_name": "cube-js/cube",
    "stargazers_count": 15689,
    "open_issues_count": 764,
    "forks_count": 1572
  },
  {
    "full_name": "grafana/tempo",
    "stargazers_count": 3037,
    "open_issues_count": 134,
    "forks_count": 382
  },
  {
    "full_name": "grafana/loki",
    "stargazers_count": 19292,
    "open_issues_count": 1053,
    "forks_count": 2775
  },
  {
    "full_name": "keichi/binary-parser",
    "stargazers_count": 692,
    "open_issues_count": 44,
    "forks_count": 125
  },
  {
    "full_name": "markotom/restify-url-semver",
    "stargazers_count": 20,
    "open_issues_count": 3,
    "forks_count": 14
  },
  {
    "full_name": "ethereum-optimism/optimism",
    "stargazers_count": 3947,
    "open_issues_count": 141,
    "forks_count": 1670
  },
  {
    "full_name": "papers-we-love/papers-we-love",
    "stargazers_count": 73254,
    "open_issues_count": 5,
    "forks_count": 5314
  },
  {
    "full_name": "google/comprehensive-rust",
    "stargazers_count": 17230,
    "open_issues_count": 90,
    "forks_count": 900
  },
  {
    "full_name": "software-jessies-org/jessies",
    "stargazers_count": 77,
    "open_issues_count": 15,
    "forks_count": 17
  },
  {
    "full_name": "grpc/grpc-web",
    "stargazers_count": 7608,
    "open_issues_count": 215,
    "forks_count": 737
  },
  {
    "full_name": "redhat-helloworld-msa/helloworld-msa",
    "stargazers_count": 227,
    "open_issues_count": 3,
    "forks_count": 165
  },
  {
    "full_name": "1kc/librazermacos",
    "stargazers_count": 17,
    "open_issues_count": 20,
    "forks_count": 31
  },
  {
    "full_name": "1kc/razer-macos",
    "stargazers_count": 1901,
    "open_issues_count": 429,
    "forks_count": 207
  },
  {
    "full_name": "boyter/searchcode-server",
    "stargazers_count": 351,
    "open_issues_count": 59,
    "forks_count": 95
  },
  {
    "full_name": "bluesky-social/atproto",
    "stargazers_count": 4379,
    "open_issues_count": 100,
    "forks_count": 278
  },
  {
    "full_name": "gnolang/gno",
    "stargazers_count": 743,
    "open_issues_count": 217,
    "forks_count": 284
  },
  {
    "full_name": "berty/go-orbit-db",
    "stargazers_count": 337,
    "open_issues_count": 7,
    "forks_count": 47
  },
  {
    "full_name": "neurodrone/crdt",
    "stargazers_count": 240,
    "open_issues_count": 8,
    "forks_count": 24
  },
  {
    "full_name": "rust-crdt/rust-crdt",
    "stargazers_count": 1120,
    "open_issues_count": 18,
    "forks_count": 51
  },
  {
    "full_name": "berty/berty",
    "stargazers_count": 6787,
    "open_issues_count": 112,
    "forks_count": 328
  },
  {
    "full_name": "automerge/automerge-classic",
    "stargazers_count": 14771,
    "open_issues_count": 77,
    "forks_count": 4083
  },
  {
    "full_name": "rivo/tview",
    "stargazers_count": 8399,
    "open_issues_count": 98,
    "forks_count": 485
  },
  {
    "full_name": "quarkiverse/quarkus-renarde",
    "stargazers_count": 55,
    "open_issues_count": 27,
    "forks_count": 12
  },
  {
    "full_name": "DistributedClocks/GoVector",
    "stargazers_count": 170,
    "open_issues_count": 15,
    "forks_count": 33
  },
  {
    "full_name": "gsharma/vector-clock",
    "stargazers_count": 7,
    "open_issues_count": 4,
    "forks_count": 2
  },
  {
    "full_name": "qwlabs/vector-clock",
    "stargazers_count": 4,
    "open_issues_count": 0,
    "forks_count": 0
  }
]